liboc/math/__init__.py
liboc/math/signal_strength.py
liboc.math-0.1.1.dist-info/METADATA
liboc.math-0.1.1.dist-info/WHEEL
liboc.math-0.1.1.dist-info/top_level.txt
liboc.math-0.1.1.dist-info/RECORD
